LICENSE
MANIFEST.in
README.md
setup.py
dantejsoncoder/__init__.py
dantejsoncoder/apps.py
dantejsoncoder/coder.py
django_dantejsoncoder.egg-info/PKG-INFO
django_dantejsoncoder.egg-info/SOURCES.txt
django_dantejsoncoder.egg-info/dependency_links.txt
django_dantejsoncoder.egg-info/top_level.txt