Metadata-Version: 1.0
Name: django-dantejsoncoder
Version: 0.1
Summary: A simple Django app to covert standard django-models to json
Home-page: https://github.com/DanteOnline/django-dantejsoncoder
Author: DanteOnline
Author-email: iamdanteonline@gmail.com
License: GNU General Public License v3.0
Platform: UNKNOWN
